{
  "run_id": "20251104_163218__unknown_aug_degraded",
  "source_run_id": "20251104_163218__unknown",
  "material": "Steel_3_8_in",
  "condition": "0_5_kg_Ea_Peg",
  "health_label": "Degraded",
  "health_label_source": "synthetic_degraded_spikes",
  "cruise_rms_g": 0.08059,
  "is_augmented": true,
  "augmentation": {
    "tier": "degraded",
    "amplitude_g": 0.3,
    "sigma_ms": 8,
    "spike_count": 4,
    "spikes": [
      {
        "row_index": 9455,
        "time_ms": 1454612,
        "amplitude_g": 0.3,
        "sign": -1
      },
      {
        "row_index": 7908,
        "time_ms": 1453067,
        "amplitude_g": 0.3,
        "sign": -1
      },
      {
        "row_index": 7264,
        "time_ms": 1452429,
        "amplitude_g": 0.3,
        "sign": 1
      },
      {
        "row_index": 8295,
        "time_ms": 1453455,
        "amplitude_g": 0.3,
        "sign": -1
      }
    ],
    "random_seed": 42
  },
  "weight_kg": 0.5,
  "weight_location": null,
  "weight_distribution": "each_peg",
  "speed_fps": null,
  "load_level": null,
  "is_unclipped": false
}