{
  "run_id": "20251104_143425__unknown_aug_degraded",
  "source_run_id": "20251104_143425__unknown",
  "material": "Aluminum_1_2_in",
  "condition": "4kg_Location_A",
  "health_label": "Degraded",
  "health_label_source": "synthetic_degraded_spikes",
  "cruise_rms_g": 0.0729,
  "is_augmented": true,
  "augmentation": {
    "tier": "degraded",
    "amplitude_g": 0.3,
    "sigma_ms": 8,
    "spike_count": 5,
    "spikes": [
      {
        "row_index": 8134,
        "time_ms": 2095673,
        "amplitude_g": 0.3,
        "sign": 1
      },
      {
        "row_index": 8717,
        "time_ms": 2096258,
        "amplitude_g": 0.3,
        "sign": -1
      },
      {
        "row_index": 7129,
        "time_ms": 2094662,
        "amplitude_g": 0.3,
        "sign": -1
      },
      {
        "row_index": 7951,
        "time_ms": 2095498,
        "amplitude_g": 0.3,
        "sign": 1
      },
      {
        "row_index": 6467,
        "time_ms": 2094013,
        "amplitude_g": 0.3,
        "sign": -1
      }
    ],
    "random_seed": 42
  },
  "weight_kg": 4.0,
  "weight_location": "A",
  "weight_distribution": null,
  "speed_fps": null,
  "load_level": null,
  "is_unclipped": false
}